bible_io/__init__.py
bible_io/bible_book_enums.py
bible_io/bible_class.py
bible_io/book.py
bible_io/chapter.py
bible_io/definitions.py
bible_io/errors.py
bible_io/verse.py
bible_io/py.typed
bible_io-1.0.2.dist-info/METADATA
bible_io-1.0.2.dist-info/WHEEL
bible_io-1.0.2.dist-info/licenses/LICENSE
bible_io-1.0.2.dist-info/RECORD
