Metadata-Version: 2.4
Name: bible-io
Version: 1.0.2
Summary: Bible parsing package
Project-URL: Homepage, https://github.com/m0ty/bible-io-package-py
Author: Moty Fainer
License-Expression: MIT
License-File: LICENSE
Classifier: Operating System :: OS Independent
Classifier: Programming Language :: Python :: 3
Classifier: Typing :: Typed
Requires-Python: >=3.10
Requires-Dist: mypy>=1.19.1
